{
    "test": "ceci est un test FRANCAIS",
    "loading": "Loading",
    "back": "Back",
    "search": "Search",
    "previous": "Previous",
    "next": "Next",
    "connecting": "Connecting",
    "logout": "Logout",
    "name": "Last Name",
    "firstName": "First Name",
    "phone": "Phone",
    "pwd": "Password",
    "article": "article",
    "liked": "liked",
    "like": "like",
    "email": "Email",
    "message": "Message",
    "contactBtn": "Contact",
    "errorPage": {
        "title": "404 - Page not found",
        "description": "Sorry, this page doesn't exist!"
    },
    "articleDetail": {
        "articleNotFound": "Article not found",
        "author": "Author"
    },
    "articles": {
        "title": "List of Articles",
        "placeholder": "Search for an article (title, description, author...)",
        "loadingArticles": "Loading articles"
    },
    "contact": {
        "opinion": "Your opinion matters!",
        "description": "Your feedback is essential for us to improve! Share your experience, tell us what you like and what we could improve. Your suggestions help us make this blog an even more useful and enriching resource.",
        "form": {
            "messageSend": "Your message has been sent successfully:",
            "satisfactionPositive": "😊 We're delighted to know you like it!",
            "satisfactionNegative": "😞 We are sad to know that you do not like it."
        }
    },
    "exploreWeb": {
        "h1": "Explore the",
        "web": "Web",
        "inAll": "in all",
        "its": "its",
        "facets": "facets",
        "description": "The web is constantly evolving, and we're here to guide you through its trends, technologies, and best practices. Whether you're a developer, designer, or digital enthusiast, our blog offers quality content to keep you ahead of the curve.",
        "discoveryArticle": "Discover the articles",
        "subscribeNewsletter": "Subscribe to the Newsletter"
    },
    "trust": {
        "title": "They trust us"
    },
    "learn": {
        "description": "Whether you are a beginner in web development or an expert looking to deepen your knowledge, we offer tutorials, guides and best practices to help you learn effectively.",
        "h2": "Learn",
        "and": "and",
        "progress": "progress",
        "p": "resources for all levels",
        "explore": "Explore the resources"
    },
    "stayTuned": {
        "p": "The web, a constantly evolving ecosystem",
        "description": "Every week, we analyze the latest web trends: emerging frameworks, SEO best practices, accessibility, and much more. Don't miss any digital news!",
        "link": "Read recent articles",
        "title:": "Stay informed about the latest",
        "tendancies": "trends"
    },
    "signup": {
        "signup": "Sign up",
        "forgotPwd": "Forgot your password?",
        "github": "Sign up with GithHub"
    },
    "login": {
        "login": "Log in",
        "forgotPwd": "Forgot your password?",
        "noAccount": "Don't have an account? You can",
        "noAccount2": "create one.",
        "github": "Log in with GithHub"
    },
    "profile": {
        "articleCreated": "Article successfully created!",
        "activity": "Activity",
        "noArticleLiked": "You haven't liked any articles yet.",
        "lastLiked": "Last article liked:",
        "loadingArticles": "Loading articles",
        "noArticle": "You haven't written any articles yet.",
        "writeArticle": "Want to write an article?",
        "publishArticle": "Publish article",
        "publishForm": {
            "title": "Title (minimum 5 characters)",
            "description": "Article description",
            "image": "Image link (optional)"
        }
    },
    "delete": {
        "deleteArticle": "Delete the article?",
        "description": "This action is irreversible. The article will be permanently deleted.",
        "cancel": "Cancel",
        "delete": "Delete",
        "articleDeleted": "Article deleted"
    },
    "header": {
        "login": "Log in",
        "signup": "Sign up"
    }
}